smartduck/loaders/apis/__init__.py
smartduck/loaders/apis/facebook.py
smartduck/loaders/base/loader.py
smartduck-0.1.1.dist-info/METADATA
smartduck-0.1.1.dist-info/WHEEL
smartduck-0.1.1.dist-info/top_level.txt
smartduck-0.1.1.dist-info/RECORD
