Metadata-Version: 2.4
Name: smartduck
Version: 0.1.1
Summary: Data engineering toolkit with DuckDB
Requires-Python: >=3.11
Requires-Dist: dlt[duckdb]>=1.17.1
Requires-Dist: jupyter>=1.1.1
Requires-Dist: numpy>=2.3.4
Requires-Dist: pandas>=2.3.3
Requires-Dist: polars>=1.34.0
Requires-Dist: python-dotenv>=1.1.1
Requires-Dist: requests>=2.32.5
